pet/__init__.py
pet/this.py
pet/datasets/__init__.py
pet/datasets/_compat.py
pet/datasets/_constants.py
pet/datasets/_paths.py
pet/datasets/_resources.py
pet/datasets/_textbook.py
pet/datasets/b.cmd
pet/datasets/factory.py
pet/datasets/generators.py
pet/datasets/loaders.py
pet/datasets/stats.py
pet/datasets/sysinfo.py
pet/datasets/tree.py
pet/datasets/__pycache__/__init__.cpython-311.pyc
pet/datasets/__pycache__/_compat.cpython-311.pyc
pet/datasets/__pycache__/_constants.cpython-311.pyc
pet/datasets/__pycache__/_paths.cpython-311.pyc
pet/datasets/__pycache__/_resources.cpython-311.pyc
pet/datasets/__pycache__/_textbook.cpython-311.pyc
pet/datasets/__pycache__/factory.cpython-311.pyc
pet/datasets/__pycache__/generators.cpython-311.pyc
pet/datasets/__pycache__/loaders.cpython-311.pyc
pet/datasets/__pycache__/stats.cpython-311.pyc
pet/datasets/__pycache__/sysinfo.cpython-311.pyc
pet/datasets/__pycache__/tree.cpython-311.pyc
pet/datasets/database/2022pst.xlsx
pet/datasets/database/2022tsk.xlsx
pet/datasets/database/2022zzy.xlsx
pet/datasets/database/2023-2024-1.xlsx
pet/datasets/database/2023-2024-2.xlsx
pet/datasets/database/20231118-players.xlsx
pet/datasets/database/2023QS.xlsx
pet/datasets/database/2023ejkg.txt
pet/datasets/database/2023xkjs.xlsx
pet/datasets/database/2023zzy-ok.xlsx
pet/datasets/database/2023zzy.xlsx
pet/datasets/database/64gx.xlsx
pet/datasets/database/China_universities .xlsx
pet/datasets/database/Edu_subjects.xlsx
pet/datasets/database/__init__.py
pet/datasets/database/beijing-subway.xlsx
pet/datasets/database/beijing_bus.xlsx
pet/datasets/database/bg.xlsx
pet/datasets/database/cylj.txt
pet/datasets/database/ddj.txt
pet/datasets/database/ejkg.txt
pet/datasets/database/error.txt
pet/datasets/database/htys.txt
pet/datasets/database/ip_address.xlsx
pet/datasets/database/iris.xlsx
pet/datasets/database/sample_cookies.txt
pet/datasets/database/shanghai-subway.xlsx
pet/datasets/database/ssq_22134.xlsx
pet/datasets/database/st.xlsx
python_education_tools-26.2.48.dist-info/METADATA
python_education_tools-26.2.48.dist-info/WHEEL
python_education_tools-26.2.48.dist-info/entry_points.txt
python_education_tools-26.2.48.dist-info/top_level.txt
python_education_tools-26.2.48.dist-info/RECORD
