Metadata-Version: 2.4
Name: Python_Education_Tools
Version: 26.2.48
Summary: Python Education Tools for Teaching
Home-page: https://github.com/liluqun
Author: Prof.Luqun Li
Author-email: liluqun@gmail.com
Project-URL: Bug Tracker, https://github.com/liluqun
Classifier: Programming Language :: Python :: 3
Classifier: License :: OSI Approved :: MIT License
Classifier: Operating System :: OS Independent
Requires-Python: >=3.8
Requires-Dist: numpy
Requires-Dist: pandas
Requires-Dist: matplotlib
Requires-Dist: openpyxl
Requires-Dist: importlib-resources; python_version < "3.9"
Provides-Extra: audio
Requires-Dist: pyttsx3; extra == "audio"
Requires-Dist: pydub; extra == "audio"
Provides-Extra: image
Requires-Dist: pillow; extra == "image"
Provides-Extra: sys
Requires-Dist: psutil; extra == "sys"
Provides-Extra: stats
Requires-Dist: scipy; extra == "stats"
Provides-Extra: viz
Requires-Dist: seaborn; extra == "viz"
Requires-Dist: wordcloud; extra == "viz"
Provides-Extra: web
Requires-Dist: requests-html; extra == "web"
Provides-Extra: full
Requires-Dist: pyttsx3; extra == "full"
Requires-Dist: pydub; extra == "full"
Requires-Dist: pillow; extra == "full"
Requires-Dist: psutil; extra == "full"
Requires-Dist: scipy; extra == "full"
Requires-Dist: seaborn; extra == "full"
Requires-Dist: wordcloud; extra == "full"
Requires-Dist: requests-html; extra == "full"
